.gitignore
.hgignore
.travis.yml
AUTHORS
CHANGELOG.md
Changelog
LICENSE
MANIFEST.in
Makefile
README.md
TODO
poetry.lock
pyproject.toml
pytest.ini
setup.py
tox.ini
.github/workflows/test.yml
doc/INSTALL
doc/INSTALL.rus.txt
doc/README.rus.txt
doc/WEBFRAMEWORKS.rus.txt
doc/examples/dt.distance_of_time_in_words.py
doc/examples/dt.ru_strftime.py
doc/examples/numeral.choose_plural.py
doc/examples/numeral.in_words.py
doc/examples/numeral.rubles.py
doc/examples/numeral.sum_string.py
doc/examples/test.py
doc/examples/translit.py
doc/examples-django/README
doc/examples-django/pytilsex/__init__.py
doc/examples-django/pytilsex/manage.py
doc/examples-django/pytilsex/settings.py
doc/examples-django/pytilsex/tests.py
doc/examples-django/pytilsex/urls.py
doc/examples-django/pytilsex/__pycache__/__init__.cpython-310.pyc
doc/examples-django/pytilsex/__pycache__/__init__.cpython-311.pyc
doc/examples-django/pytilsex/__pycache__/settings.cpython-310.pyc
doc/examples-django/pytilsex/__pycache__/settings.cpython-311.pyc
doc/examples-django/pytilsex/__pycache__/tests.cpython-310-pytest-7.0.1.pyc
doc/examples-django/pytilsex/__pycache__/tests.cpython-310.pyc
doc/examples-django/pytilsex/__pycache__/urls.cpython-310.pyc
doc/examples-django/pytilsex/static/css/style.css
doc/examples-django/pytilsex/static/images/header_inner.png
doc/examples-django/pytilsex/templates/base.html
doc/examples-django/pytilsex/templates/dt.html
doc/examples-django/pytilsex/templates/numeral.html
doc/examples-django/pytilsex/templates/translit.html
doc/examples/__pycache__/test.cpython-310-pytest-7.0.1.pyc
pytils/__init__.py
pytils/dt.py
pytils/numeral.py
pytils/translit.py
pytils/typo.py
pytils/utils.py
pytils.egg-info/PKG-INFO
pytils.egg-info/SOURCES.txt
pytils.egg-info/dependency_links.txt
pytils.egg-info/top_level.txt
pytils.egg-info/zip-safe
pytils/templatetags/__init__.py
pytils/templatetags/pytils_dt.py
pytils/templatetags/pytils_numeral.py
pytils/templatetags/pytils_translit.py
pytils/test/__init__.py
pytils/test/test_dt.py
pytils/test/test_numeral.py
pytils/test/test_translit.py
pytils/test/test_typo.py
pytils/test/test_utils.py
